mkdocs_charts_plugin/__init__.py
mkdocs_charts_plugin/fences.py
mkdocs_charts_plugin/plugin.py
mkdocs_charts_plugin/utils.py
mkdocs_charts_plugin/js/mkdocs-charts-plugin.js
mkdocs_charts_plugin-0.0.13.dist-info/licenses/LICENSE
mkdocs_charts_plugin-0.0.13.dist-info/METADATA
mkdocs_charts_plugin-0.0.13.dist-info/WHEEL
mkdocs_charts_plugin-0.0.13.dist-info/entry_points.txt
mkdocs_charts_plugin-0.0.13.dist-info/top_level.txt
mkdocs_charts_plugin-0.0.13.dist-info/RECORD
